Metadata-Version: 2.4
Name: md-qvalue
Version: 0.2.3
Summary: Calculates the fraction of native contacts conserved during the simulation
Author-email: Carlos Bueno <carlos.bueno@rice.edu>
Maintainer-email: Carlos Bueno <carlos.bueno@rice.edu>
License:                     GNU GENERAL PUBLIC LICENSE
Keywords: molecular simulations
Requires-Python: >=3.9
License-File: LICENSE
License-File: AUTHORS.md
Requires-Dist: MDAnalysis>=2.0.0
Provides-Extra: test
Requires-Dist: pytest>=6.0; extra == "test"
Requires-Dist: pytest-xdist>=2.5; extra == "test"
Requires-Dist: pytest-cov>=3.0; extra == "test"
Provides-Extra: doc
Requires-Dist: sphinx; extra == "doc"
Requires-Dist: sphinx_rtd_theme; extra == "doc"
Dynamic: license-file
